unofficial_xitroo_api-0.9.1.dist-info/licenses/LICENSE
xitroo/Captcha.py
xitroo/Inbox.py
xitroo/Mail.py
xitroo/Search.py
xitroo/Xitroo.py
xitroo/__init__.py
xitroo/endpoints.py
xitroo/exceptions.py
unofficial_xitroo_api-0.9.1.dist-info/METADATA
unofficial_xitroo_api-0.9.1.dist-info/WHEEL
unofficial_xitroo_api-0.9.1.dist-info/top_level.txt
unofficial_xitroo_api-0.9.1.dist-info/RECORD
