Metadata-Version: 2.4
Name: unofficial_xitroo_api
Version: 0.9.1
Summary: Xitroo API
Home-page: https://github.com/Th3K1n91/unofficial-xitroo-api/tree/main
Author: Th3K1n91
Author-email: x.xxha001@gmail.com
Project-URL: Bug Tracker, https://github.com/Th3K1n91/unofficial-xitroo-api/issues
Classifier: Programming Language :: Python :: 3
Classifier: License :: OSI Approved :: MIT License
Classifier: Operating System :: OS Independent
Requires-Python: >=3.6
License-File: LICENSE
Dynamic: license-file
